Metadata-Version: 2.1
Name: pydps
Version: 0.1.3
Summary: Small package contains Python implementations of frequently used design patterns.
Home-page: https://github.com/hieupth/pydps
Author: Hieu Pham
Author-email: hieupt.ai@gmail.com
License: MIT
Download-URL: https://github.com/hieupth/pydps/archive/v_01.tar.gz
Keywords: design patterns
Platform: UNKNOWN
Classifier: Development Status :: 1 - Planning
Classifier: Intended Audience :: Developers
Classifier: Topic :: Software Development :: Build Tools
Classifier: License :: OSI Approved :: MIT License
Classifier: Programming Language :: Python :: 3
Classifier: Programming Language :: Python :: 3.6
Classifier: Programming Language :: Python :: 3.7
Classifier: Programming Language :: Python :: 3.8
License-File: LICENSE
